pylwdrone/__init__.py
pylwdrone/__main__.py
pylwdrone/command.py
pylwdrone/defaults.py
pylwdrone/lwdrone.py
pylwdrone/responses.py
pylwdrone/utils.py
pylwdrone-0.5.0.dist-info/LICENSE
pylwdrone-0.5.0.dist-info/METADATA
pylwdrone-0.5.0.dist-info/WHEEL
pylwdrone-0.5.0.dist-info/entry_points.txt
pylwdrone-0.5.0.dist-info/top_level.txt
pylwdrone-0.5.0.dist-info/RECORD
