Metadata-Version: 2.1
Name: pylwdrone
Version: 0.5.0
Summary: communicate with a lewei camera module
Home-page: https://github.com/meekworth/pylwdrone
Author: meekworth
Author-email: meekworth@gmail.com
License: Apache License, Version 2.0
Platform: UNKNOWN
Classifier: Programming Language :: Python :: 3
Classifier: License :: OSI Approved :: Apache Software License
Classifier: Operating System :: OS Independent
Classifier: Programming Language :: Python :: 3
Classifier: Programming Language :: Python :: 3.7
Classifier: Programming Language :: Python :: 3.8
Classifier: Topic :: Software Development :: Libraries :: Python Modules
Classifier: Topic :: Utilities
Requires-Python: >=3.7
License-File: LICENSE
